examples/__init__.py
examples/basic_usage.py
examples/data_generation_example.py
examples/manual_vs_nn_compare.py
manual_model/__init__.py
manual_model/embeddings.py
manual_model/train.py
nn_model/__init__.py
nn_model/model.py
nn_model/train.py
nn_model/utils.py
nn_model/visualization.py
tests/__init__.py
tests/test_nn_embeddings.py
training_data/__init__.py
training_data/data.py
training_data/training_pairs.py
valuevec-0.1.0.dist-info/licenses/LICENSE
valuevec-0.1.0.dist-info/METADATA
valuevec-0.1.0.dist-info/WHEEL
valuevec-0.1.0.dist-info/top_level.txt
valuevec-0.1.0.dist-info/RECORD
