Metadata-Version: 2.4
Name: valuevec
Version: 0.1.0
Summary: Value-based word embeddings that incorporate external continuous values.
Home-page: https://github.com/rdoku/valuevec
Author: Ronald Doku
Author-email: Ronald Doku <ronjeffdoku@gmail.com>
License: MIT
Project-URL: Homepage, https://github.com/rdoku/valuevec
Project-URL: Documentation, https://www.rondoku.com/project/10
Project-URL: Source, https://github.com/rdoku/valuevec
Project-URL: Issues, https://github.com/rdoku/valuevec/issues
Requires-Python: >=3.6
License-File: LICENSE
Requires-Dist: torch>=1.7.0
Requires-Dist: pandas>=1.0.0
Requires-Dist: numpy>=1.19.0
Requires-Dist: matplotlib>=3.3.0
Requires-Dist: scikit-learn>=0.23.0
Dynamic: author
Dynamic: home-page
Dynamic: license-file
Dynamic: requires-python
